Metadata-Version: 2.4
Name: yt-dlp-coomer
Version: 1.2.0
Author-email: Schmoaaaaah <schmoaaaaah@r4nd0.com>
License: This is free and unencumbered software released into the public domain.
Requires-Python: >=3.11
License-File: LICENSE
Requires-Dist: yt-dlp>=2025.03.31
Dynamic: license-file
